SNFit/__init__.py
SNFit/lc_analysis.py
SNFit/lightcurve.py
SNFit/load_file.py
SNFit/plot.py
SNFit/data_dir/bolometric_11fe.txt
SNFit/data_dir/sn2017eaw_B.csv
SNFit/data_dir/sn2017eaw_I.csv
SNFit/data_dir/sn2017eaw_R.csv
SNFit/data_dir/sn2017eaw_U.csv
SNFit/data_dir/sn2017eaw_V.csv
snfit-1.1.2.dist-info/licenses/LICENSE
snfit-1.1.2.dist-info/METADATA
snfit-1.1.2.dist-info/WHEEL
snfit-1.1.2.dist-info/entry_points.txt
snfit-1.1.2.dist-info/top_level.txt
snfit-1.1.2.dist-info/RECORD
