Metadata-Version: 2.4
Name: SNFit
Version: 1.1.2
License-File: LICENSE
Requires-Dist: numpy
Requires-Dist: dash
Requires-Dist: plotly
Requires-Dist: matplotlib
Requires-Dist: pandas
Requires-Dist: pytest
Dynamic: license-file
